terraform_initializer/__init__.py
terraform_initializer/cli.py
terraform_initializer/templates/variables.tf
terraform_initializer/templates/aws/provider.tf
terraform_initializer/templates/azure/provider.tf
terraform_initializer/templates/gcp/provider.tf
terraform_initializer/templates/local/provider.tf
terraform_initializer-0.1.0.dist-info/licenses/LICENSE
terraform_initializer-0.1.0.dist-info/METADATA
terraform_initializer-0.1.0.dist-info/WHEEL
terraform_initializer-0.1.0.dist-info/entry_points.txt
terraform_initializer-0.1.0.dist-info/top_level.txt
terraform_initializer-0.1.0.dist-info/RECORD
