Metadata-Version: 2.4
Name: terraform_initializer
Version: 0.1.0
Summary: CLI tool to initialize Terraform projects with standard files
Author-email: Aman Walekar <amanwalekar11@gmail.com>
License-Expression: MIT
Requires-Python: >=3.7
License-File: LICENSE
Dynamic: license-file
